etc/flowd/flowd.cfg
scitags/__init__.py
scitags/config.py
scitags/service.py
scitags/settings.py
scitags/backends/__init__.py
scitags/backends/ebpf.py
scitags/backends/prometheus.py
scitags/backends/udp_firefly.py
scitags/netlink/__init__.py
scitags/netlink/cache.py
scitags/netlink/cache_ss.py
scitags/netlink/pyroute_tcp.py
scitags/plugins/__init__.py
scitags/plugins/firefly.py
scitags/plugins/iperf.py
scitags/plugins/netlink.py
scitags/plugins/netstat.py
scitags/plugins/np_api.py
scitags/stun/__init__.py
scitags/stun/services.py
usr/lib/systemd/system/flowd.service
usr/sbin/flowd
flowd-1.1.2.dist-info/LICENSE
flowd-1.1.2.dist-info/METADATA
flowd-1.1.2.dist-info/WHEEL
flowd-1.1.2.dist-info/top_level.txt
flowd-1.1.2.dist-info/RECORD
